pickled_database
